crypto/__init__.py
crypto/bitget.py
crypto/gate.py
mecli/__init__.py
mecli/bitget.py
mecli/example.py
mecli/gate.py
mecli/util.py
utils/__init__.py
utils/elapsed.py
utils/logger.py
utils/mysql.py
utils/pd.py
utils/sleep.py
mecli_py-0.1.1.dist-info/METADATA
mecli_py-0.1.1.dist-info/WHEEL
mecli_py-0.1.1.dist-info/entry_points.txt
mecli_py-0.1.1.dist-info/RECORD
