Metadata-Version: 2.4
Name: mecli-py
Version: 0.1.1
Summary: my cli tool
Project-URL: Homepage, https://pypi.org/project/mecli-py
Project-URL: Repository, https://github.com/meme2046/mecli-py
License: MIT
Classifier: Intended Audience :: Developers
Classifier: License :: OSI Approved :: MIT License
Classifier: Programming Language :: Python :: 3
Requires-Python: >=3.10
Requires-Dist: arrow>=1.4.0
Requires-Dist: babel>=2.17.0
Requires-Dist: cowsay>=6.1
Requires-Dist: dotenv>=0.9.9
Requires-Dist: pandas>=2.3.3
Requires-Dist: pymysql>=1.1.2
Requires-Dist: pytz>=2025.2
Requires-Dist: requests[socks]>=2.32.5
Requires-Dist: sqlalchemy>=2.0.45
Requires-Dist: typer>=0.20.0
